pydantic_converter/__init__.py
pydantic_converter/__main__.py
pydantic_converter/cli.py
pydantic_converter/marker.py
pydantic_converter/py.typed
pydantic_converter-0.1.4.dist-info/METADATA
pydantic_converter-0.1.4.dist-info/WHEEL
pydantic_converter-0.1.4.dist-info/entry_points.txt
pydantic_converter-0.1.4.dist-info/RECORD
