Metadata-Version: 2.3
Name: pydantic-converter
Version: 0.1.4
Summary: Convert pydantic model to other format
Author-email: Ja-sonYun <killa30867@gmail.com>
Requires-Python: >=3.9
Requires-Dist: fire>=0.6.0
Requires-Dist: pydantic>2.0
Requires-Dist: pyhumps>=3.8.0
Requires-Dist: rich>=13.7.1
